telebot_utils
